DateVersioning.py
DateVersioning-20.292.114220.dist-info/LICENSE
DateVersioning-20.292.114220.dist-info/METADATA
DateVersioning-20.292.114220.dist-info/WHEEL
DateVersioning-20.292.114220.dist-info/top_level.txt
DateVersioning-20.292.114220.dist-info/RECORD
