Metadata-Version: 2.1
Name: DateVersioning
Version: 20.292.114220
Summary: Git commit date based version generator
Home-page: https://github.com/EinarArnason/DateVersioning
Author: Einar Arnason
Author-email: einar@gmail.com
License: MIT
Platform: UNKNOWN
